MANIFEST.in
README.rst
setup.py
src/collective/__init__.py
src/collective.recipe.sphinxbuilder.egg-info/PKG-INFO
src/collective.recipe.sphinxbuilder.egg-info/SOURCES.txt
src/collective.recipe.sphinxbuilder.egg-info/dependency_links.txt
src/collective.recipe.sphinxbuilder.egg-info/entry_points.txt
src/collective.recipe.sphinxbuilder.egg-info/namespace_packages.txt
src/collective.recipe.sphinxbuilder.egg-info/not-zip-safe
src/collective.recipe.sphinxbuilder.egg-info/requires.txt
src/collective.recipe.sphinxbuilder.egg-info/top_level.txt
src/collective/recipe/__init__.py
src/collective/recipe/sphinxbuilder/__init__.py
src/collective/recipe/sphinxbuilder/utils.py
src/collective/recipe/sphinxbuilder/docs/about_sphinx.rst
src/collective/recipe/sphinxbuilder/docs/conf.py
src/collective/recipe/sphinxbuilder/docs/contributors.rst
src/collective/recipe/sphinxbuilder/docs/history.rst
src/collective/recipe/sphinxbuilder/docs/index.rst
src/collective/recipe/sphinxbuilder/docs/options.rst
src/collective/recipe/sphinxbuilder/docs/quick_start.rst
src/collective/recipe/sphinxbuilder/docs/reference.rst
src/collective/recipe/sphinxbuilder/docs/usage.rst
src/collective/recipe/sphinxbuilder/tests/__init__.py
src/collective/recipe/sphinxbuilder/tests/test_docs.py