Metadata-Version: 1.1
Name: collective.recipe.sphinxbuilder
Version: 0.8.2
Summary: ZC.buildout recipe to generate and build Sphinx-based documentation in the buildout.
Home-page: https://github.com/sdouche/collective.recipe.sphinxbuilder
Author: Tarek Ziade
Author-email: tarek@ziade.org
License: ZPL
Keywords: buildout sphinx
Platform: UNKNOWN
Classifier: Framework :: Buildout
Classifier: Intended Audience :: Developers
Classifier: Programming Language :: Python :: 2
Classifier: Programming Language :: Python :: 3
Classifier: Topic :: Software Development :: Build Tools
Classifier: Topic :: Software Development :: Libraries :: Python Modules
Classifier: License :: OSI Approved :: Zope Public License
